AUTHORS.txt
LICENSE.txt
MANIFEST.in
README.md
setup.py
menpo3d/__init__.py
menpo3d/_static_version.py
menpo3d/_version.py
menpo3d/barycentric.py
menpo3d/base.py
menpo3d/camera.py
menpo3d/checks.py
menpo3d/extractimage.py
menpo3d/math.py
menpo3d/result.py
menpo3d/unwrap.py
menpo3d/vtk_test.py
menpo3d/vtkutils.py
menpo3d.egg-info/PKG-INFO
menpo3d.egg-info/SOURCES.txt
menpo3d.egg-info/dependency_links.txt
menpo3d.egg-info/requires.txt
menpo3d.egg-info/top_level.txt
menpo3d/correspond/__init__.py
menpo3d/correspond/correspond_test.py
menpo3d/correspond/nicp.py
menpo3d/correspond/pnp.py
menpo3d/data/bunny.ljson
menpo3d/data/bunny.obj
menpo3d/data/bunny_no_nose.ljson
menpo3d/data/james.jpg
menpo3d/data/james.ljson
menpo3d/data/james.obj
menpo3d/data/james.obj.mtl
menpo3d/data/template.ljson
menpo3d/data/template.ply
menpo3d/io/__init__.py
menpo3d/io/input/__init__.py
menpo3d/io/input/base.py
menpo3d/io/input/extensions.py
menpo3d/io/input/landmark_mesh.py
menpo3d/io/input/lsfm.py
menpo3d/io/input/mesh/__init__.py
menpo3d/io/input/mesh/base.py
menpo3d/io/output/__init__.py
menpo3d/io/output/base.py
menpo3d/io/output/extensions.py
menpo3d/io/output/mesh.py
menpo3d/io/test/__init__.py
menpo3d/io/test/io_export_test.py
menpo3d/io/test/io_input_test.py
menpo3d/morphablemodel/__init__.py
menpo3d/morphablemodel/base.py
menpo3d/morphablemodel/fitter.py
menpo3d/morphablemodel/multilinear_model.py
menpo3d/morphablemodel/result.py
menpo3d/morphablemodel/shapemodel.py
menpo3d/morphablemodel/algorithm/__init__.py
menpo3d/morphablemodel/algorithm/derivatives.py
menpo3d/morphablemodel/algorithm/lk.py
menpo3d/rasterize/__init__.py
menpo3d/rasterize/base.py
menpo3d/rasterize/cpu.py
menpo3d/rasterize/opengl.py
menpo3d/rasterize/transform.py
menpo3d/rasterize/tripixel.cpp
menpo3d/rasterize/tripixel.pyx
menpo3d/rasterize/shaders/per_vertex/passthrough.frag
menpo3d/rasterize/shaders/per_vertex/passthrough.vert
menpo3d/rasterize/shaders/texture/passthrough.frag
menpo3d/rasterize/shaders/texture/passthrough.vert
menpo3d/rasterize/test/__init__.py
menpo3d/rasterize/test/shaders_test.py
menpo3d/visualize/__init__.py
menpo3d/visualize/base.py
